izza/__init__.py
izza/exploration/__init__.py
izza/exploration/visualisation.py
izza/modeling/__init__.py
izza/modeling/bagging.py
izza/modeling/feature_eng/__init__.py
izza/modeling/feature_eng/date.py
izza/modeling/feature_eng/localisation.py
izza/modeling/feature_eng/natural_language.py
izza/validation/__init__.py
izza/validation/f_macro.py
izza/validation/validation.py
izza-0.4.0.dist-info/LICENSE
izza-0.4.0.dist-info/WHEEL
izza-0.4.0.dist-info/METADATA
izza-0.4.0.dist-info/RECORD
