Metadata-Version: 2.1
Name: izza
Version: 0.4.0
Summary: my machine learning toolkit
License: BSD
Keywords: data viz,machine learning
Author: Ismael Lachheb
Author-email: ismael.lachheb@protonmail.com
Requires-Python: >=3.8,<4.0
Classifier: License :: Other/Proprietary License
Classifier: Programming Language :: Python :: 3
Classifier: Programming Language :: Python :: 3.8
Classifier: Programming Language :: Python :: 3.9
Requires-Dist: MiniSom (>=2.2.8,<3.0.0)
Requires-Dist: matplotlib (>=3.4.1,<4.0.0)
Requires-Dist: pandas (>=1.2.3,<2.0.0)
Requires-Dist: scikit-learn (>=0.24.1,<0.25.0)
